<?xml version="1.0" encoding="utf-8" ?>
<dwsync>
<file name="amazing_sunset_large.jpg" server="ftp.rabithole.com//public_html/" local="130487131251287876" remote="130488843600000000" Dst="2" />
<file name="anna_best_thumb.jpg" server="ftp.rabithole.com//public_html/" local="130486648785143467" remote="130488843600000000" Dst="2" />
<file name="anna_best_large.jpg" server="ftp.rabithole.com//public_html/" local="130487069235249564" remote="130488843600000000" Dst="2" />
<file name="baby_smile_large.jpg" server="ftp.rabithole.com//public_html/" local="130487123962876053" remote="130488843600000000" Dst="2" />
<file name="beach_sunset_large.jpg" server="ftp.rabithole.com//public_html/" local="130488161354465253" remote="130488843600000000" Dst="2" />
<file name="cloud_water_large.jpg" server="ftp.rabithole.com//public_html/" local="130487140478723649" remote="130488843600000000" Dst="2" />
<file name="disappointment_large.jpg" server="ftp.rabithole.com//public_html/" local="130488157597235257" remote="130488843600000000" Dst="2" />
<file name="cove_hdr2_large.jpg" server="ftp.rabithole.com//public_html/" local="130487893665279221" remote="130488843600000000" Dst="2" />
<file name="farm_mist_large.jpg" server="ftp.rabithole.com//public_html/" local="130487142447182546" remote="130488843600000000" Dst="2" />
<file name="farmer_chyann_large.jpg" server="ftp.rabithole.com//public_html/" local="130487129342565649" remote="130488843600000000" Dst="2" />
<file name="farm_mist_thumb.jpg" server="ftp.rabithole.com//public_html/" local="130487142788107928" remote="130488843600000000" Dst="2" />
<file name="fort_stevens_thumb.jpg" server="ftp.rabithole.com//public_html/" local="130488153914484906" remote="130488843600000000" Dst="2" />
<file name="fort_stevens_large.jpg" server="ftp.rabithole.com//public_html/" local="130488152005010147" remote="130488843600000000" Dst="2" />
<file name="goat_playing_large.jpg" server="ftp.rabithole.com//public_html/" local="130488150356373462" remote="130488843600000000" Dst="2" />
<file name="love_at_sunset_large.jpg" server="ftp.rabithole.com//public_html/" local="130488159959952030" remote="130488843600000000" Dst="2" />
<file name="lemon_large.jpg" server="ftp.rabithole.com//public_html/" local="130487922529654284" remote="130488843600000000" Dst="2" />
<file name="marina_night_thumb.jpg" server="ftp.rabithole.com//public_html/" local="130486965928298927" remote="130488843600000000" Dst="2" />
<file name="marina_night_large.jpg" server="ftp.rabithole.com//public_html/" local="130487070441945408" remote="130488843600000000" Dst="2" />
<file name="moab_large.jpg" server="ftp.rabithole.com//public_html/" local="130487138444619986" remote="130488843600000000" Dst="2" />
<file name="nehalem_stars_large.jpg" server="ftp.rabithole.com//public_html/" local="130487155836652010" remote="130488843600000000" Dst="2" />
<file name="night_fog_large.jpg" server="ftp.rabithole.com//public_html/" local="130487157193246490" remote="130488843600000000" Dst="2" />
<file name="oowee_thumb.jpg" server="ftp.rabithole.com//public_html/" local="130487917277730538" remote="130488843600000000" Dst="2" />
<file name="oowee_large.jpg" server="ftp.rabithole.com//public_html/" local="130487916931247794" remote="130488843600000000" Dst="2" />
<file name="ripples_large.jpg" server="ftp.rabithole.com//public_html/" local="130487902914225412" remote="130488843600000000" Dst="2" />
<file name="ship_large.jpg" server="ftp.rabithole.com//public_html/" local="130487901030396015" remote="130488843600000000" Dst="2" />
<file name="sink_bath_large.jpg" server="ftp.rabithole.com//public_html/" local="130487066273659574" remote="130488843600000000" Dst="2" />
<file name="space_needle_large.jpg" server="ftp.rabithole.com//public_html/" local="130487159629957481" remote="130488843600000000" Dst="2" />
<file name="sunset_kayaking_thumb.jpg" server="ftp.rabithole.com//public_html/" local="130487863324219177" remote="130488843600000000" Dst="2" />
<file name="sunset_kayaking_large.jpg" server="ftp.rabithole.com//public_html/" local="130487873420038795" remote="130488843600000000" Dst="2" />
<file name="under_bridge_large.jpg" server="ftp.rabithole.com//public_html/" local="130487866582148594" remote="130488843600000000" Dst="2" />
<file name="under_bridge_large1.jpg" server="ftp.rabithole.com//public_html/" local="130487872464421943" remote="130488843600000000" Dst="2" />
<file name="under_bridge_large2.jpg" server="ftp.rabithole.com//public_html/" local="130487867836388081" remote="130488843600000000" Dst="2" />
<file name="under_bridge_large3.jpg" server="ftp.rabithole.com//public_html/" local="130487868025081642" remote="130488843600000000" Dst="2" />
<file name="yurt_interior_large.jpg" server="ftp.rabithole.com//public_html/" local="130488148031463442" remote="130488843600000000" Dst="2" />
<file name="red_heads_thumb.jpg" server="ftp.rabithole.com//public_html/" local="130494867478749187" remote="130494904800000000" Dst="2" />
<file name="red_heads_large.jpg" server="ftp.rabithole.com//public_html/" local="130494868174073837" remote="130494904800000000" Dst="2" />
<file name="overlay.png" server="ftp.rabithole.com/public_html/cas222/" local="129823592100000000" remote="130626553800000000" Dst="1" />
<file name="controls.png" server="ftp.rabithole.com/public_html/cas222/" local="129823592100000000" remote="130626553800000000" Dst="1" />
<file name="loading_background.png" server="ftp.rabithole.com/public_html/cas222/" local="129823592100000000" remote="130626553800000000" Dst="1" />
<file name="border.png" server="ftp.rabithole.com/public_html/cas222/" local="129823592100000000" remote="130626553800000000" Dst="1" />
<file name="amazing_sunset_large.jpg" server="ftp.rabithole.com/public_html/cas222/" local="130487131251287876" remote="130626553800000000" Dst="1" />
<file name="anna_best_thumb.jpg" server="ftp.rabithole.com/public_html/cas222/" local="130486648785143467" remote="130626553800000000" Dst="1" />
<file name="anna_best_large.jpg" server="ftp.rabithole.com/public_html/cas222/" local="130487069235249564" remote="130626553800000000" Dst="1" />
<file name="baby_smile_large.jpg" server="ftp.rabithole.com/public_html/cas222/" local="130487123962876053" remote="130626553800000000" Dst="1" />
<file name="beach_sunset_large.jpg" server="ftp.rabithole.com/public_html/cas222/" local="130488161354465253" remote="130626553800000000" Dst="1" />
<file name="cloud_water_large.jpg" server="ftp.rabithole.com/public_html/cas222/" local="130487140478723649" remote="130626553800000000" Dst="1" />
<file name="cove_hdr2_large.jpg" server="ftp.rabithole.com/public_html/cas222/" local="130487893665279221" remote="130626553800000000" Dst="1" />
<file name="disappointment_large.jpg" server="ftp.rabithole.com/public_html/cas222/" local="130488157597235257" remote="130626553800000000" Dst="1" />
<file name="farm_mist_large.jpg" server="ftp.rabithole.com/public_html/cas222/" local="130487142447182546" remote="130626553800000000" Dst="1" />
<file name="farm_mist_thumb.jpg" server="ftp.rabithole.com/public_html/cas222/" local="130487142788107928" remote="130626553800000000" Dst="1" />
<file name="farmer_chyann_large.jpg" server="ftp.rabithole.com/public_html/cas222/" local="130487129342565649" remote="130626553800000000" Dst="1" />
<file name="fort_stevens_thumb.jpg" server="ftp.rabithole.com/public_html/cas222/" local="130488153914484906" remote="130626553800000000" Dst="1" />
<file name="fort_stevens_large.jpg" server="ftp.rabithole.com/public_html/cas222/" local="130488152005010147" remote="130626553800000000" Dst="1" />
<file name="love_at_sunset_large.jpg" server="ftp.rabithole.com/public_html/cas222/" local="130488159959952030" remote="130626553800000000" Dst="1" />
<file name="lemon_large.jpg" server="ftp.rabithole.com/public_html/cas222/" local="130487922529654284" remote="130626553800000000" Dst="1" />
<file name="goat_playing_large.jpg" server="ftp.rabithole.com/public_html/cas222/" local="130488150356373462" remote="130626553800000000" Dst="1" />
<file name="marina_night_thumb.jpg" server="ftp.rabithole.com/public_html/cas222/" local="130486965928298927" remote="130626553800000000" Dst="1" />
<file name="marina_night_large.jpg" server="ftp.rabithole.com/public_html/cas222/" local="130487070441945408" remote="130626553800000000" Dst="1" />
<file name="nehalem_stars_large.jpg" server="ftp.rabithole.com/public_html/cas222/" local="130487155836652010" remote="130626553800000000" Dst="1" />
<file name="moab_large.jpg" server="ftp.rabithole.com/public_html/cas222/" local="130487138444619986" remote="130626553800000000" Dst="1" />
<file name="night_fog_large.jpg" server="ftp.rabithole.com/public_html/cas222/" local="130487157193246490" remote="130626553800000000" Dst="1" />
<file name="oowee_thumb.jpg" server="ftp.rabithole.com/public_html/cas222/" local="130487917277730538" remote="130626553800000000" Dst="1" />
<file name="red_heads_thumb.jpg" server="ftp.rabithole.com/public_html/cas222/" local="130494867478749187" remote="130626553800000000" Dst="1" />
<file name="oowee_large.jpg" server="ftp.rabithole.com/public_html/cas222/" local="130487916931247794" remote="130626553800000000" Dst="1" />
<file name="ripples_large.jpg" server="ftp.rabithole.com/public_html/cas222/" local="130487902914225412" remote="130626553800000000" Dst="1" />
<file name="ship_large.jpg" server="ftp.rabithole.com/public_html/cas222/" local="130487901030396015" remote="130626553800000000" Dst="1" />
<file name="red_heads_large.jpg" server="ftp.rabithole.com/public_html/cas222/" local="130494868174073837" remote="130626553800000000" Dst="1" />
<file name="sink_bath_large.jpg" server="ftp.rabithole.com/public_html/cas222/" local="130487066273659574" remote="130626553800000000" Dst="1" />
<file name="space_needle_large.jpg" server="ftp.rabithole.com/public_html/cas222/" local="130487159629957481" remote="130626553800000000" Dst="1" />
<file name="sunset_kayaking_thumb.jpg" server="ftp.rabithole.com/public_html/cas222/" local="130487863324219177" remote="130626553800000000" Dst="1" />
<file name="sunset_kayaking_large.jpg" server="ftp.rabithole.com/public_html/cas222/" local="130487873420038795" remote="130626553800000000" Dst="1" />
<file name="under_bridge_large.jpg" server="ftp.rabithole.com/public_html/cas222/" local="130487866582148594" remote="130626553800000000" Dst="1" />
<file name="under_bridge_large1.jpg" server="ftp.rabithole.com/public_html/cas222/" local="130487872464421943" remote="130626553800000000" Dst="1" />
<file name="under_bridge_large2.jpg" server="ftp.rabithole.com/public_html/cas222/" local="130487867836388081" remote="130626553800000000" Dst="1" />
<file name="under_bridge_large3.jpg" server="ftp.rabithole.com/public_html/cas222/" local="130487868025081642" remote="130626553800000000" Dst="1" />
<file name="yurt_interior_large.jpg" server="ftp.rabithole.com/public_html/cas222/" local="130488148031463442" remote="130626553800000000" Dst="1" />
<file name="border.png" server="ftp.rabithole.com//public_html/" local="129823592100000000" remote="130632490800000000" Dst="1" />
<file name="controls.png" server="ftp.rabithole.com//public_html/" local="129823592100000000" remote="130632490800000000" Dst="1" />
<file name="loading_background.png" server="ftp.rabithole.com//public_html/" local="129823592100000000" remote="130632490800000000" Dst="1" />
<file name="overlay.png" server="ftp.rabithole.com//public_html/" local="129823592100000000" remote="130632490800000000" Dst="1" />
</dwsync>